bioscan_dataset/__init__.py
bioscan_dataset/__meta__.py
bioscan_dataset/bioscan1m.py
bioscan_dataset/bioscan5m.py
bioscan_dataset-1.3.0.dist-info/licenses/LICENSE
bioscan_dataset-1.3.0.dist-info/METADATA
bioscan_dataset-1.3.0.dist-info/WHEEL
bioscan_dataset-1.3.0.dist-info/top_level.txt
bioscan_dataset-1.3.0.dist-info/RECORD
