Metadata-Version: 2.4
Name: bioscan-dataset
Version: 1.3.0
Summary: PyTorch torchvision-style datasets for BIOSCAN-1M and BIOSCAN-5M.
Home-page: https://github.com/bioscan-ml/dataset
Author: Scott C. Lowe
Author-email: scott.code.lowe@gmail.com
License: MIT
Project-URL: Documentation, https://bioscan-dataset.readthedocs.io
Project-URL: Source Code, https://github.com/bioscan-ml/dataset
Project-URL: Bug Tracker, https://github.com/bioscan-ml/dataset/issues
Project-URL: Citation, https://arxiv.org/abs/2406.12723
Classifier: Development Status :: 5 - Production/Stable
Classifier: Intended Audience :: Science/Research
Classifier: License :: OSI Approved :: MIT License
Classifier: Natural Language :: English
Classifier: Operating System :: OS Independent
Classifier: Programming Language :: Python
Classifier: Programming Language :: Python :: 3
Classifier: Programming Language :: Python :: 3.8
Classifier: Programming Language :: Python :: 3.9
Classifier: Programming Language :: Python :: 3.10
Classifier: Programming Language :: Python :: 3.11
Classifier: Programming Language :: Python :: 3.12
Classifier: Topic :: Scientific/Engineering
Classifier: Topic :: Scientific/Engineering :: Artificial Intelligence
Classifier: Topic :: Scientific/Engineering :: Bio-Informatics
Classifier: Topic :: Scientific/Engineering :: Image Recognition
Requires-Python: >=3.8
License-File: LICENSE
Requires-Dist: numpy>=1.21.0
Requires-Dist: pandas>=1.0.0
Requires-Dist: Pillow>=4.1.1
Requires-Dist: torch>=1.4.0
Requires-Dist: torchvision>=0.6.0
Provides-Extra: dev
Requires-Dist: black==25.1.0; extra == "dev"
Requires-Dist: identify>=1.4.20; extra == "dev"
Requires-Dist: pre-commit>=3.2.0; extra == "dev"
Provides-Extra: docs
Requires-Dist: Jinja2>=3.0; extra == "docs"
Requires-Dist: myst-parser; extra == "docs"
Requires-Dist: pypandoc>=1.6.3; extra == "docs"
Requires-Dist: readthedocs-sphinx-search; python_version >= "3.6" and extra == "docs"
Requires-Dist: sphinx>=6.0.0; extra == "docs"
Requires-Dist: sphinx-autobuild; extra == "docs"
Requires-Dist: sphinx_rtd_theme; extra == "docs"
Requires-Dist: sphinxcontrib-googleanalytics>=0.4; extra == "docs"
Requires-Dist: watchdog<1.0.0; python_version < "3.6" and extra == "docs"
Provides-Extra: all
Requires-Dist: Jinja2>=3.0; extra == "all"
Requires-Dist: black==25.1.0; extra == "all"
Requires-Dist: identify>=1.4.20; extra == "all"
Requires-Dist: myst-parser; extra == "all"
Requires-Dist: pre-commit>=3.2.0; extra == "all"
Requires-Dist: pypandoc>=1.6.3; extra == "all"
Requires-Dist: readthedocs-sphinx-search; python_version >= "3.6" and extra == "all"
Requires-Dist: sphinx-autobuild; extra == "all"
Requires-Dist: sphinx>=6.0.0; extra == "all"
Requires-Dist: sphinx_rtd_theme; extra == "all"
Requires-Dist: sphinxcontrib-googleanalytics>=0.4; extra == "all"
Requires-Dist: watchdog<1.0.0; python_version < "3.6" and extra == "all"
Dynamic: author
Dynamic: author-email
Dynamic: classifier
Dynamic: description
Dynamic: description-content-type
Dynamic: home-page
Dynamic: license
Dynamic: license-file
Dynamic: project-url
Dynamic: provides-extra
Dynamic: requires-dist
Dynamic: requires-python
Dynamic: summary
